gpt_muti_gen/__init__.py
gpt_muti_gen/api.py
gpt_muti_gen/cgpt_wp.py
gpt_muti_gen/chatgpt.py
gpt_muti_gen/libs/__init__.py
gpt_muti_gen/libs/json_conf.py
gpt_muti_gen/libs/yml_conf.py
gpt_muti_gen-1.0.9.dist-info/LICENSE
gpt_muti_gen-1.0.9.dist-info/METADATA
gpt_muti_gen-1.0.9.dist-info/WHEEL
gpt_muti_gen-1.0.9.dist-info/entry_points.txt
gpt_muti_gen-1.0.9.dist-info/top_level.txt
gpt_muti_gen-1.0.9.dist-info/RECORD
