Metadata-Version: 2.1
Name: gpt-muti-gen
Version: 1.0.9
Summary: A tool to mutiply generate text with chatgpt
Home-page: https://git.yoqi.me/openai/chatgpt-wordpress
Author: lyq
Author-email: liuyuqi.gov@msn.cn
License: Apache License Version 2.0
Classifier: Topic :: Software Development :: Libraries :: Python Modules
Classifier: Programming Language :: Python :: 3.8
Classifier: Programming Language :: Python :: 3.9
Classifier: Programming Language :: Python :: 3.10
Classifier: Programming Language :: Python :: 3.11
License-File: LICENSE
Requires-Dist: requests (==2.19.1)
Provides-Extra: dev
Requires-Dist: pytest ; extra == 'dev'
